infuradj/__init__.py
infuradj/lib.py
infuradj-1.0.1.dist-info/LICENSE
infuradj-1.0.1.dist-info/METADATA
infuradj-1.0.1.dist-info/WHEEL
infuradj-1.0.1.dist-info/top_level.txt
infuradj-1.0.1.dist-info/RECORD
