Metadata-Version: 2.1
Name: infuradj
Version: 1.0.1
Summary: Send tx from Django with infura
Home-page: https://github.com/dastanbeksamatov/django-infura
Author: Dastan Samatov
Author-email: dastanbeksamatov@gmail.com
License: MIT
Platform: UNKNOWN
Classifier: License :: OSI Approved :: MIT License
Classifier: Programming Language :: Python
Classifier: Programming Language :: Python :: 2
Classifier: Programming Language :: Python :: 3
Requires-Dist: web3 (==5.20.0)
